mc_zouz-2.0.0.data/purelib/MCMC/__init__.py
mc_zouz-2.0.0.data/purelib/MCMC/maxmumclique.cp39-win_amd64.pyd
mc_zouz-2.0.0.data/purelib/MCMC/maxmumclique.cpython-38-x86_64-linux-gnu.so
mc_zouz-2.0.0.dist-info/LICENSE.txt
mc_zouz-2.0.0.dist-info/METADATA
mc_zouz-2.0.0.dist-info/WHEEL
mc_zouz-2.0.0.dist-info/top_level.txt
mc_zouz-2.0.0.dist-info/RECORD
