Metadata-Version: 2.1
Name: mc-zouz
Version: 2.0.0
Summary: Algotirhm to find maximalclique
Home-page: UNKNOWN
Author: UNKNOWN
Author-email: UNKNOWN
License: UNKNOWN
Platform: UNKNOWN
